Workbook

Sheet MM
D1: Monthly of June26 Balance sheet
A3: Income | C3: Expenses | F3: Savings | J3: Interest | N3: ITC
A4: Name | B4: Amount | C4: S.no | D4: Description | E4: Amount | F4: S.no | G4: Description | H4: Amount | J4: Debt
A5: Husband | C5: 1 | D5: House Rent | F5: 1 | G5: Grow | J5: Divident | K5: =SUM(O3:O1018) -> 0
A6: Wife | C6: 2 | D6: Personal care | E6: ='Personal care'!D33+'Personal care'!I33 -> 0 | F6: 2 | G6: Mutual Fund (Nandha)paytm | J6: Total | K6: =SUM(K3:K5) -> 0
A7: brother | C7: 3 | D7: Electricity Bill (Home) | F7: 3 | G7: Mutual Fund (Archana)
A8: Archana | C8: 4 | D8: Airtel Internet bill | E8: 0 | F8: 4 | G8: PPF (Nandha) | J8: Walllet | K8: 5531
A9: Mutual | C9: 5 | D9: Gifts | F9: 5 | G9: Coin | J9: Cash
A10: ACT | C10: 6 | D10: Kayal | E10: ='Snacks & enterinment'!O33 -> 0 | F10: 6 | G10: FD | J10: Total BL
A11: Mutual | C11: 7 | D11: TAX | E11: 0 | F11: 7 | G11: LIC Premium
A12: Previous | C12: 8 | D12: Phone Recharge's | E12: ='Phone Recharges'!B12 -> 0 | F12: 8 | G12: PayTM Gold | J12: Account | K12: =B32-K8 -> -5531
A13: Previous adj | C13: 9 | D13: Groceries & Veg/Non Veg & fruits other | E13: ='Groceries & Vegtables'!B8 -> 0 | F13: 9 | G13: Stock Market IN
A14: divident | C14: 10 | D14: Snacks and Shopping | E14: ='Snacks & enterinment'!B8 -> 0 | F14: 10 | G14: Post office saving
C15: 11 | D15: Travelling | E15: =Travel!C33 -> 0 | F15: 11 | G15: Indian Bank (Archana)
A16: refund | C16: 12 | D16: Medical expenses | E16: =Medical!C33 -> 0 | F16: 12 | G16: Post Office (Archana)
C17: 13 | D17: Health Insurance Family | E17: 0 | F17: 13 | G17: SBI
A18: loan | C18: 14 | D18: Archana | F18: 14 | G18: IDBI
A19: cc | C19: 15 | D19: Nandha Home | F19: 15 | G19: Post office digi (Archana)
C20: 16 | D20: HDFC Term insurance | F20: 16 | G20: Hundial
C21: 17 | D21: IDFC CC Payment | E21: 0 | F21: 17 | G21: Gold for kayal
C22: 18 | D22: Axis CC Payment | E22: 0 | F22: 18 | G22: Bond
C23: 19 | D23: HDFC CC Payment | F23: 19 | G23: SSA
C24: 20 | D24: HDFC UPI Credit | G24: Stock Market US | L24: Loan | M24: Current | N24: Paid
C25: 21 | D25: Education and Traning | E25: =Education!C33 -> 0 | J25: Loan
C26: 22 | D26: Tour | E26: =tour!B37 -> 0 | J26: S.no | K26: Description
A27: Total | B27: =SUM(B5:B25) -> 0 | C27: Total Expenses | E27: =SUM(E5:E26) -> 0 | F27: Total Savings | H27: =SUM(H5:H25) -> 0 | J27: 1
A30: Earning | B30: =B27 -> 0
A31: Expenses + Savings | B31: =E27+H27 -> 0
A32: Balance | B32: =B27-B31 -> 0
A33: cash on hand | B33: =B32+K6 -> 0
A34: HDFC Credit card 💳 | B34: =Credit_Card_Pay!D26 -> 0
A35: Axis Credit card 💳 | B35: =Credit_Card_Pay!I26 -> 0
A36: HDFC UPI Credit card 💳 | B36: =Credit_Card_Pay!N26 -> 0
A37: IDFC | B37: =Credit_Card_Pay!S26 -> 0
A38: Petty Loan | B38: =Credit_Card_Pay!X26 -> 0
A39: Total | B39: =SUM(B34:B38) -> 0

Sheet Phone Recharges
A1: Names | B1: Amount | C1: Date
A2: Jio
A3: Appa
A4: Amma
A5: DTH
A6: Archana
A7: Amazon
A8: Zee
A9: Netflix
A10: Airtel WIFI
A11: sundirect
A12: Total | B12: =SUM(B2:B11) -> 0

Sheet Groceries & Vegtables
A1: Descrition | B1: Amount | C1: Date | E1: Date | F1: Grocery Items | G1: Amount | I1: Date | J1: Veg/Fruit Items | K1: Amount | M1: Date | N1: Non-veg/Egg Items | O1: Amount | Q1: Date | R1: Grocery Home | S1: Amount
A2: Milk | E2: 1 | I2: 1 | M2: 1 | Q2: 1
A3: Non Veg/Egg | B3: =O33 -> 0 | E3: 2 | I3: 2 | M3: 2 | Q3: 2
A4: Vegetable's /Fruits | B4: =K33 -> 0 | E4: 3 | I4: 3 | M4: 3 | Q4: 3
A5: Grocery | B5: =G33 -> 0 | E5: 4 | I5: 4 | M5: 4 | Q5: 4
A6: Grocery (Home) | B6: =S6 -> 0 | E6: 5 | I6: 5 | M6: 5 | Q6: Total | S6: =sum(S2:S5) -> 0
A7: other | E7: 6 | I7: 6 | M7: 6
A8: Total | B8: =SUM(B2:B7) -> 0 | E8: 7 | I8: 7 | M8: 7
E9: 8 | I9: 8 | M9: 8
E10: 9 | I10: 9 | M10: 9
E11: 10 | I11: 10 | M11: 10
E12: 11 | I12: 11 | M12: 11
E13: 12 | I13: 12 | M13: 12
E14: 13 | I14: 13 | M14: 13
E15: 14 | I15: 14 | M15: 14
E16: 15 | I16: 15 | M16: 15
E17: 16 | I17: 16 | M17: 16
E18: 17 | I18: 17 | M18: 17
E19: 18 | I19: 18 | M19: 18
E20: 19 | I20: 19 | M20: 19
... E32: 31 | I32: 31 | M32: 31
F33: Grocery Total | G33: =SUM(G2:G32) -> 0 | J33: Veg Total | K33: =SUM(K2:K32) -> 0 | N33: Meat Total | O33: =SUM(O2:O32) -> 0

Sheet Snacks & enterinment
A1: Descrition | B1: Amount | C1: Date | E1: Date | F1: Food | G1: Amount | I1: Date | J1: Shopping | K1: Amount | M1: Date | N1: kayal | O1: Amount | Q1: Date | R1: Movie | S1: Amount
A2: Movie | E2: 1 | I2: 1 | M2: 1 | Q2: 1
A3: Shopping | B3: =K33 -> 0 | E3: 2 | I3: 2 | M3: 2 | Q3: 2
A4: Snacks/Outside food | B4: =G33 -> 0 | E4: 3 | I4: 3 | M4: 3 | Q4: 3
A5: Movie | B5: =S33 -> 0 | E5: 4 | I5: 4 | M5: 4 | Q5: 4
E6: 5 | I6: 5 | M6: 5 | Q6: 5
E7: 6 | I7: 6 | M7: 6 | Q7: 6
A8: Total | B8: =SUM(B2:B7) -> 0 | E8: 7 | I8: 7 | M8: 7 | Q8: 7
E9: 8 | I9: 8 | M9: 8 | Q9: 8
E10: 9 | I10: 9 | M10: 9 | Q10: 9
E11: 10 | I11: 10 | M11: 10 | Q11: 10
E12: 11 | I12: 11 | M12: 11 | Q12: 11
E13: 12 | I13: 12 | M13: 12 | Q13: 12
E14: 13 | I14: 13 | M14: 13 | Q14: 13
E15: 14 | I15: 14 | M15: 14 | Q15: 14
E16: 15 | I16: 15 | M16: 15 | Q16: 15
E17: 16 | I17: 16 | M17: 16 | Q17: 16
E18: 17 | I18: 17 | M18: 17 | Q18: 17
E19: 18 | I19: 18 | M19: 18 | Q19: 18
E20: 19 | I20: 19 | M20: 19 | Q20: 19
... E32: 31 | I32: 31 | M32: 31 | Q32: 31
E33: Food Total | G33: =SUM(G2:G32) -> 0 | I33: Shopping Total | K33: =SUM(K2:K32) -> 0 | M33: Shopping Total | O33: =SUM(O2:O32) -> 0 | Q33: Shopping Total | S33: =SUM(S2:S32) -> 0

Sheet Personal care
B1: Date | C1: Nandha Personal care | D1: Amount | G1: Date | H1: Archane Personal care | I1: Amount
B2: 1 | G2: 1
B3: 2 | G3: 2
B4: 3 | G4: 3
B5: 4 | G5: 4
B6: 5 | G6: 5
B7: 6 | G7: 6
B8: 7 | G8: 7
B9: 8 | G9: 8
B10: 9 | G10: 9
B11: 10 | G11: 10
B12: 11 | G12: 11
B13: 12 | G13: 12
... B32: 31 | G32: 31
B33: Total | D33: =SUM(D2:D32) -> 0 | G33: Total | I33: =SUM(I2:I32) -> 0

Sheet Medical
A1: Date | B1: Medical | C1: Amount
A2: 1
A3: 2
A4: 3
A5: 4
A6: 5
A7: 6
A8: 7
A9: 8
A10: 9
A11: 10
A12: 11
A13: 12
... A32: 31
B33: Medi Total | C33: =SUM(C2:C32) -> 0

Sheet Travel
A1: Date | B1: Travel | C1: Amount
A2: 1
A3: 2
A4: 3
A5: 4
A6: 5
A7: 6
A8: 7
A9: 8
A10: 9
A11: 10
A12: 11
A13: 12
... A32: 31
B33: Medi Total | C33: =SUM(C2:C32) -> 0

Sheet Education
A1: Date | B1: Education and Training | C1: Amount
A2: 1
A3: 2
A4: 3
A5: 4
A6: 5
A7: 6
A8: 7
A9: 8
A10: 9
A11: 10
A12: 11
A13: 12
... A32: 31
B33: Medi Total | C33: =SUM(C2:C32) -> 0

Sheet tour
A1: Date | B1: Transport | C1: Amount | E1: Date | F1: Food | G1: Amount | I1: Date | J1: Stay | K1: Amount | M1: Date | N1: Entry fees | O1: Amount | Q1: Date | R1: Shopping | S1: Amount | U1: Date | V1: Food | W1: Amount
A2: 1 | E2: 1 | I2: 1 | M2: 1 | Q2: 1 | U2: 1
A3: 2 | E3: 2 | I3: 2 | M3: 2 | Q3: 2 | U3: 2
A4: 3 | E4: 3 | I4: 3 | M4: 3 | Q4: 3 | U4: 3
A5: 4 | E5: 4 | I5: 4 | M5: 4 | Q5: 4 | U5: 4
A6: 5 | E6: 5 | I6: 5 | M6: 5 | Q6: 5 | U6: 5
A7: 6 | E7: 6 | I7: 6 | M7: 6 | Q7: 6 | U7: 6
A8: 7 | E8: 7 | I8: 7 | M8: 7 | Q8: 7 | U8: 7
A9: 8 | E9: 8 | I9: 8 | M9: 8 | Q9: 8 | U9: 8
A10: 9 | E10: 9 | I10: 9 | M10: 9 | Q10: 9 | U10: 9
A11: 10 | E11: 10 | I11: 10 | M11: 10 | Q11: 10 | U11: 10
A12: 11 | E12: 11 | I12: 11 | M12: 11 | Q12: 11 | U12: 11
A13: 12 | E13: 12 | I13: 12 | M13: 12 | Q13: 12 | U13: 12
... A32: 31 | E32: 31 | I32: 31 | M32: 31 | Q32: 31 | U32: 31
B33: Total | C33: =SUM(C2:C32) -> 0 | F33: Total | G33: =SUM(G2:G32) -> 0 | J33: Total | K33: =SUM(K2:K32) -> 0 | N33: Total | O33: =SUM(O2:O32) -> 0 | R33: Total | S33: =SUM(S2:S32) -> 0 | V33: Total | W33: =SUM(W2:W32) -> 0
A37: Total | B37: =C33+G33+K33+O33+S33+W33 -> 0

Sheet Credit_Card_Pay
A1: SNo | B1: Card | C1: Details | D1: Amount | F1: SNo | G1: Card | H1: Details | I1: Amount | K1: SNo | L1: Card | M1: Details | N1: Amount | P1: SNo | Q1: Card | R1: Details | S1: Amount | U1: SNo | V1: Loan | W1: Details | X1: Amount
A2: 1 | B2: HDFC | F2: 1 | G2: AXIS | K2: 1 | L2: HDFC UPI | P2: 1 | Q2: IDFC | U2: 1
A3: 2 | B3: HDFC | F3: 2 | G3: AXIS | K3: 2 | L3: HDFC UPI | P3: 2 | Q3: IDFC
A4: 3 | B4: HDFC | F4: 3 | G4: AXIS | K4: 3 | L4: HDFC UPI | P4: 3 | Q4: IDFC
A5: 4 | B5: HDFC | F5: 4 | G5: AXIS | K5: 4 | L5: HDFC UPI | P5: 4 | Q5: IDFC
A6: 5 | B6: HDFC | F6: 5 | G6: AXIS | K6: 5 | L6: HDFC UPI
A7: 6 | B7: HDFC | F7: 6 | G7: AXIS | K7: 6 | L7: HDFC UPI
A8: 7 | B8: HDFC | F8: 7 | G8: AXIS | K8: 7 | L8: HDFC UPI
A9: 8 | B9: HDFC | F9: 8 | G9: AXIS | K9: 8 | L9: HDFC UPI
A10: 9 | B10: HDFC | F10: 9 | G10: AXIS | K10: 9 | L10: HDFC UPI
A11: 10 | B11: HDFC | F11: 10 | G11: AXIS | K11: 10 | L11: HDFC UPI
A12: 11 | B12: HDFC | F12: 11 | G12: AXIS | K12: 11 | L12: HDFC UPI
A13: 12 | B13: HDFC | F13: 12 | G13: AXIS | K13: 12 | L13: HDFC UPI
A22: 13 | B22: HDFC | F22: 13 | G22: AXIS | K22: 13 | L22: HDFC UPI
A23: 14 | B23: HDFC | F23: 14 | G23: AXIS | K23: 14 | L23: HDFC UPI
A25: 15 | B25: HDFC | F25: 15 | G25: AXIS | K25: 15 | L25: HDFC UPI
A26: Total | D26: =SUM(D2:D25) -> 0 | F26: Total | I26: =SUM(I2:I25) -> 0 | K26: Total | N26: =SUM(N2:N25) -> 0 | P26: Total | S26: =SUM(S2:S25) -> 0 | U26: Total | X26: =SUM(X2:X25) -> 0
